fastapi_di_kit/__init__.py
fastapi_di_kit/container.py
fastapi_di_kit/decorators.py
fastapi_di_kit/fastapi_integration.py
fastapi_di_kit/lazy.py
fastapi_di_kit/py.typed
fastapi_di_kit/types.py
fastapi_di_kit-0.1.0.dist-info/METADATA
fastapi_di_kit-0.1.0.dist-info/WHEEL
fastapi_di_kit-0.1.0.dist-info/licenses/LICENSE
fastapi_di_kit-0.1.0.dist-info/RECORD
