Metadata-Version: 2.4
Name: fastapi-di-kit
Version: 0.1.0
Summary: A simple, powerful dependency injection library for FastAPI supporting hexagonal architecture
Project-URL: Homepage, https://github.com/tonlls1999/fastapi-di-kit
Project-URL: Documentation, https://github.com/tonlls1999/fastapi-di-kit#readme
Project-URL: Repository, https://github.com/tonlls1999/fastapi-di-kit
Project-URL: Issues, https://github.com/tonlls1999/fastapi-di-kit/issues
Project-URL: Changelog, https://github.com/tonlls1999/fastapi-di-kit/blob/main/CHANGELOG.md
Author-email: Ton Llucia <tonlls1999@gmail.com>
License: MIT
License-File: LICENSE
Keywords: clean-architecture,container,dependency-injection,di,fastapi,hexagonal-architecture
Classifier: Development Status :: 4 - Beta
Classifier: Framework :: FastAPI
Classifier: Intended Audience :: Developers
Classifier: License :: OSI Approved :: MIT License
Classifier: Programming Language :: Python :: 3
Classifier: Programming Language :: Python :: 3.12
Classifier: Programming Language :: Python :: 3.13
Classifier: Topic :: Software Development :: Libraries :: Application Frameworks
Classifier: Topic :: Software Development :: Libraries :: Python Modules
Classifier: Typing :: Typed
Requires-Python: >=3.12
Requires-Dist: fastapi>=0.104.0
Requires-Dist: typing-extensions>=4.8.0
Requires-Dist: uvicorn>=0.24.0
Provides-Extra: dev
Requires-Dist: httpx>=0.25.0; extra == 'dev'
Requires-Dist: pytest-asyncio>=0.21.0; extra == 'dev'
Requires-Dist: pytest>=7.4.0; extra == 'dev'
